pytest_env/__init__.py
pytest_env/plugin.py
pytest_env/py.typed
pytest_env/version.py
pytest_env-1.1.4.dist-info/METADATA
pytest_env-1.1.4.dist-info/WHEEL
pytest_env-1.1.4.dist-info/entry_points.txt
pytest_env-1.1.4.dist-info/licenses/LICENSE
pytest_env-1.1.4.dist-info/RECORD
