Metadata-Version: 2.3
Name: pytest-env
Version: 1.1.4
Summary: pytest plugin that allows you to add environment variables.
Project-URL: Homepage, https://github.com/pytest-dev/pytest-env
Project-URL: Source, https://github.com/pytest-dev/pytest-env
Project-URL: Tracker, https://github.com/pytest-dev/pytest-env/issues
Maintainer-email: Bernát Gábor <gaborjbernat@gmail.com>
License: MIT License
License-File: LICENSE
Keywords: env,pytest
Classifier: Development Status :: 5 - Production/Stable
Classifier: Intended Audience :: Developers
Classifier: License :: OSI Approved :: MIT License
Classifier: Operating System :: OS Independent
Classifier: Programming Language :: Python
Classifier: Programming Language :: Python :: 3 :: Only
Classifier: Programming Language :: Python :: 3.8
Classifier: Programming Language :: Python :: 3.9
Classifier: Programming Language :: Python :: 3.10
Classifier: Programming Language :: Python :: 3.11
Classifier: Programming Language :: Python :: 3.12
Classifier: Programming Language :: Python :: 3.13
Classifier: Programming Language :: Python :: Implementation :: CPython
Classifier: Topic :: Software Development :: Libraries :: Python Modules
Requires-Python: >=3.8
Requires-Dist: pytest>=8.3.2
Requires-Dist: tomli>=2.0.1; python_version < '3.11'
Provides-Extra: test
Requires-Dist: covdefaults>=2.3; extra == 'test'
Requires-Dist: coverage>=7.6.1; extra == 'test'
Requires-Dist: pytest-mock>=3.14; extra == 'test'
